tweetshot/__init__.py
tweetshot/cli_scripts.py
tweetshot/take_screenshot.py
tweetshot/tests/__init__.py
tweetshot/tests/test_take_screenshot.py
tweetshot/webdrivers/__init__.py
tweetshot/webdrivers/chrome.py
tweetshot/webdrivers/driver.py
tweetshot/webdrivers/firefox.py
tweetshot/webdrivers/set_webdriver.py
tweetshot-0.0.1.dist-info/LICENSE
tweetshot-0.0.1.dist-info/METADATA
tweetshot-0.0.1.dist-info/WHEEL
tweetshot-0.0.1.dist-info/entry_points.txt
tweetshot-0.0.1.dist-info/top_level.txt
tweetshot-0.0.1.dist-info/RECORD
