Metadata-Version: 2.1
Name: tweetshot
Version: 0.0.1
Summary: Take a tweet screenshot
Home-page: https://github.com/averdones/tweetshot
Author: Antonio Verdone
Author-email: averdones@gmail.com
License: UNKNOWN
Keywords: keyframes iframes video extractor
Platform: UNKNOWN
Classifier: Programming Language :: Python :: 3.6
Classifier: Programming Language :: Python :: 3.7
Classifier: Programming Language :: Python :: 3.8
Classifier: License :: OSI Approved :: MIT License
Classifier: Operating System :: OS Independent
Requires-Python: >=3.6
Requires-Dist: selenium (>=3.14)
Requires-Dist: pillow (>=7.1.2)
Requires-Dist: webdriver-manager (>=2.5.2)
